kivy_garden/posani.py
kivy_garden_posani-0.3.2.dist-info/WHEEL
kivy_garden_posani-0.3.2.dist-info/METADATA
kivy_garden_posani-0.3.2.dist-info/RECORD
