Metadata-Version: 2.4
Name: kivy-garden-posani
Version: 0.3.2
Summary: Automatically animates changes in widget positions
Author: Nattōsai Mitō
Author-email: Nattōsai Mitō <flow4re2c@gmail.com>
License-Expression: MIT
Requires-Python: >=3.10
Project-URL: Repository, https://github.com/gottadiveintopython/posani
